global_land_mask/__init__.py
global_land_mask/elevation01_import_single_globe_tile.py
global_land_mask/elevation02_import_and_save_all_globe_tiles.py
global_land_mask/elevation03_make_global_land_mask.py
global_land_mask/example_check_if_land.py
global_land_mask/example_plot_globe_map.py
global_land_mask/example_speed_compare.py
global_land_mask/globe.py
global_land_mask/globe_combined_mask_compressed.npz
global_land_mask-1.0.0.dist-info/LICENSE
global_land_mask-1.0.0.dist-info/METADATA
global_land_mask-1.0.0.dist-info/WHEEL
global_land_mask-1.0.0.dist-info/top_level.txt
global_land_mask-1.0.0.dist-info/RECORD
