Metadata-Version: 2.1
Name: global-land-mask
Version: 1.0.0
Summary: Check whether a lat/lon point in on land or on sea
Home-page: https://github.com/toddkarin/global-land-mask
Author: toddkarin
Author-email: pvtools.lbl@gmail.com
License: UNKNOWN
Platform: UNKNOWN
Classifier: Programming Language :: Python :: 3
Classifier: License :: OSI Approved :: MIT License
Classifier: Operating System :: OS Independent
